claude/.gitignore
claude/core/__init__.py
claude/core/app.py
claude/core/chat_manager.py
claude/core/tools.py
claude/core/widgets.py
claude/llm/__init__.py
claude/llm/ollama_client.py
celex-0.0.4.dist-info/METADATA
celex-0.0.4.dist-info/WHEEL
celex-0.0.4.dist-info/RECORD
