Metadata-Version: 2.3
Name: CeleX
Version: 0.0.4
Summary: Claude Code - An AI-powered code assistant with comprehensive tools
License: MIT
Keywords: ai,code-assistant,llm,claude,development
Author: OpenClaudeCode Team
Requires-Python: >=3.11,<4.0
Classifier: License :: OSI Approved :: MIT License
Classifier: Programming Language :: Python :: 3
Classifier: Programming Language :: Python :: 3.11
Classifier: Programming Language :: Python :: 3.12
Classifier: Programming Language :: Python :: 3.13
Project-URL: Repository, https://github.com/openclaudecode/openclaudecode
